hopx_ai/__init__.py
hopx_ai/_agent_client.py
hopx_ai/_async_agent_client.py
hopx_ai/_async_cache.py
hopx_ai/_async_client.py
hopx_ai/_async_commands.py
hopx_ai/_async_env_vars.py
hopx_ai/_async_files.py
hopx_ai/_async_files_clean.py
hopx_ai/_async_terminal.py
hopx_ai/_base_commands.py
hopx_ai/_client.py
hopx_ai/_parsers.py
hopx_ai/_sandbox_utils.py
hopx_ai/_token_cache.py
hopx_ai/_utils.py
hopx_ai/_ws_client.py
hopx_ai/async_sandbox.py
hopx_ai/cache.py
hopx_ai/commands.py
hopx_ai/desktop.py
hopx_ai/env_vars.py
hopx_ai/errors.py
hopx_ai/files.py
hopx_ai/models.py
hopx_ai/sandbox.py
hopx_ai/terminal.py
hopx_ai/_generated/__init__.py
hopx_ai/_generated/models.py
hopx_ai/template/__init__.py
hopx_ai/template/build_flow.py
hopx_ai/template/builder.py
hopx_ai/template/file_hasher.py
hopx_ai/template/ready_checks.py
hopx_ai/template/tar_creator.py
hopx_ai/template/types.py
hopx_ai-0.5.0.dist-info/METADATA
hopx_ai-0.5.0.dist-info/WHEEL
hopx_ai-0.5.0.dist-info/RECORD
